flask_acsecure/__init__.py
flask_acsecure/middleware.py
Flask_ACSecure-0.1.2.dist-info/LICENSE
Flask_ACSecure-0.1.2.dist-info/METADATA
Flask_ACSecure-0.1.2.dist-info/WHEEL
Flask_ACSecure-0.1.2.dist-info/top_level.txt
Flask_ACSecure-0.1.2.dist-info/RECORD
