Metadata-Version: 2.1
Name: Flask-ACSecure
Version: 0.1.2
Summary: Access Secure Flask Middleware
Home-page: https://github.com/TrentaIcedCoffee/access-secure
Author: Xin Jin
Author-email: opposcript@gmail.com
License: MIT
Keywords: Flask,log,anti-spam
Platform: OS Independent
Classifier: Programming Language :: Python :: 3
Classifier: License :: OSI Approved :: MIT License
Classifier: Operating System :: OS Independent
Requires-Python: >=3.5
Requires-Dist: certifi (==2019.11.28)
Requires-Dist: chardet (==3.0.4)
Requires-Dist: Click (==7.0)
Requires-Dist: Flask (==1.1.1)
Requires-Dist: idna (==2.8)
Requires-Dist: itsdangerous (==1.1.0)
Requires-Dist: Jinja2 (==2.11.1)
Requires-Dist: MarkupSafe (==1.1.1)
Requires-Dist: requests (==2.22.0)
Requires-Dist: urllib3 (==1.25.8)
Requires-Dist: Werkzeug (==1.0.0)
